dartmouth_langchain/__init__.py
dartmouth_langchain/base.py
dartmouth_langchain/cross_encoders.py
dartmouth_langchain/definitions.py
dartmouth_langchain/embeddings.py
dartmouth_langchain/llms.py
dartmouth_langchain/retrievers/__init__.py
dartmouth_langchain/retrievers/document_compressors.py
langchain_dartmouth/__init__.py
langchain_dartmouth/base.py
langchain_dartmouth/cross_encoders.py
langchain_dartmouth/definitions.py
langchain_dartmouth/embeddings.py
langchain_dartmouth/llms.py
langchain_dartmouth/retrievers/__init__.py
langchain_dartmouth/retrievers/document_compressors.py
dartmouth_langchain-0.2.7.dist-info/LICENSE
dartmouth_langchain-0.2.7.dist-info/METADATA
dartmouth_langchain-0.2.7.dist-info/WHEEL
dartmouth_langchain-0.2.7.dist-info/top_level.txt
dartmouth_langchain-0.2.7.dist-info/RECORD
