Metadata-Version: 2.1
Name: dartmouth_langchain
Version: 0.2.7
Summary: LangChain components for Dartmouth-hosted models.
Author-email: Simon Stone <simon.stone@dartmouth.edu>
Project-URL: Homepage, https://github.com/Dartmouth-Libraries/dartmouth-langchain
Project-URL: Issues, https://github.com/Dartmouth-Libraries/dartmouth-langchain/issues
Classifier: Programming Language :: Python :: 3
Classifier: License :: OSI Approved :: MIT License
Classifier: Operating System :: OS Independent
Requires-Python: >=3.10
License-File: LICENSE
Requires-Dist: dartmouth-auth
Requires-Dist: langchain
Requires-Dist: langchain-community
Requires-Dist: langchain-huggingface
Requires-Dist: langchain-openai
Requires-Dist: text-generation
Requires-Dist: python-dotenv
